gaps/__init__.py
gaps/_cli.py
gaps/_version.py
gaps/batch.py
gaps/collection.py
gaps/config.py
gaps/exceptions.py
gaps/hpc.py
gaps/legacy.py
gaps/log.py
gaps/pipeline.py
gaps/project_points.py
gaps/status.py
gaps/utilities.py
gaps/warn.py
gaps/cli/__init__.py
gaps/cli/batch.py
gaps/cli/cli.py
gaps/cli/collect.py
gaps/cli/command.py
gaps/cli/config.py
gaps/cli/documentation.py
gaps/cli/execution.py
gaps/cli/pipeline.py
gaps/cli/preprocessing.py
gaps/cli/reset.py
gaps/cli/script.py
gaps/cli/status.py
gaps/cli/templates.py
nrel_gaps-0.8.11.dist-info/licenses/LICENSE
nrel_gaps-0.8.11.dist-info/METADATA
nrel_gaps-0.8.11.dist-info/WHEEL
nrel_gaps-0.8.11.dist-info/entry_points.txt
nrel_gaps-0.8.11.dist-info/top_level.txt
nrel_gaps-0.8.11.dist-info/RECORD
