Metadata-Version: 2.4
Name: NREL-gaps
Version: 0.8.11
Summary: National Renewable Energy Laboratory's (NREL's) Geospatial Analysis Pipelines (GAPs) framework
Author-email: Paul Pinchuk <ppinchuk@nrel.gov>
Maintainer-email: Paul Pinchuk <ppinchuk@nrel.gov>, Grant Buster <gbuster@nrel.gov>
License-Expression: BSD-3-Clause
Project-URL: homepage, https://github.com/NREL/gaps
Project-URL: documentation, https://nrel.github.io/gaps/
Project-URL: repository, https://github.com/NREL/gaps
Keywords: gaps,NREL
Classifier: Development Status :: 4 - Beta
Classifier: Intended Audience :: Science/Research
Classifier: Natural Language :: English
Classifier: Programming Language :: Python :: 3.9
Classifier: Programming Language :: Python :: 3.10
Classifier: Programming Language :: Python :: 3.11
Classifier: Programming Language :: Python :: 3.12
Classifier: Programming Language :: Python :: 3.13
Classifier: Topic :: Software Development :: Libraries :: Application Frameworks
Requires-Python: >=3.9
License-File: LICENSE
Requires-Dist: click>=8.1.8
Requires-Dist: colorama>=0.4.6
Requires-Dist: NREL-rex>=0.4.3
Requires-Dist: numpy>=2.0.2
Requires-Dist: numpydoc>=1.8.0
Requires-Dist: pandas>=2.2.3
Requires-Dist: psutil>=7.0.0
Requires-Dist: pyjson5>=1.6.4
Requires-Dist: pyyaml>=6.0.2
Requires-Dist: sphinx>=7.4.7
Requires-Dist: sphinx-click>=6.0.0
Requires-Dist: sphinx-copybutton>=0.5.2
Requires-Dist: sphinx-tabs>=3.4.1
Requires-Dist: sphinxcontrib-mermaid>=1.0.0
Requires-Dist: tabulate>=0.9.0
Requires-Dist: toml>=0.10.2
Provides-Extra: dev
Requires-Dist: ipython<9,>=8.18.1; extra == "dev"
Requires-Dist: jupyter<2,>=1.1.1; extra == "dev"
Requires-Dist: pipreqs<0.5,>=0.4.13; extra == "dev"
Requires-Dist: ruff<0.9,>=0.8.0; extra == "dev"
Provides-Extra: test
Requires-Dist: flaky<4,>=3.8.1; extra == "test"
Requires-Dist: h5py<4,>=3.13.0; extra == "test"
Requires-Dist: pytest<9,>=8.3.5; extra == "test"
Requires-Dist: pytest-cases<4,>=3.8.6; extra == "test"
Requires-Dist: pytest-cov>=3.0; extra == "test"
Requires-Dist: pytest-profiling<2,>=1.7.0; extra == "test"
Requires-Dist: pytest-xdist>=3.0; extra == "test"
Requires-Dist: snakeviz<3,>=2.2.2; extra == "test"
Requires-Dist: tox<5,>=4.25.0; extra == "test"
Provides-Extra: doc
Requires-Dist: ghp-import>=2.1; extra == "doc"
Requires-Dist: make>=0.1; extra == "doc"
Requires-Dist: myst-parser<4,>=3.0.1; extra == "doc"
Requires-Dist: pandoc<3,>=2.4; extra == "doc"
Requires-Dist: pydata-sphinx-theme<0.17,>=0.16.1; extra == "doc"
Requires-Dist: setuptools<81,>=80.1.0; extra == "doc"
Provides-Extra: build
Requires-Dist: build<2,>=1.2.2; extra == "build"
Requires-Dist: pkginfo<2,>=1.12.1.2; extra == "build"
Requires-Dist: twine<7,>=6.1.0; extra == "build"
Dynamic: license-file
